{"name":"should_be_able_to_identify_the_application_with_page_objects","id":"net.serenitybdd.demos.todos.pageobjects.features.accessing_the_application.LearnAboutTheApplication:should_be_able_to_identify_the_application_with_page_objects","testCaseName":"net.serenitybdd.demos.todos.pageobjects.features.accessing_the_application.LearnAboutTheApplication","testSteps":[{"number":1,"description":"Starts with an empty todo list","duration":1228,"startTime":"2022-02-13T09:37:34.435726920Z[Etc/UTC]","screenshots":[{"screenshot":"a385aec9d35a6fc7f4eb9c6069bbb0e4b3317c3d623e54fd3195ad5d99d9ebe7.png","timeStamp":1644745055664}],"result":"SUCCESS","precondition":false,"level":0,"children":[{"number":2,"description":"Starts with a todo list containing: {}","duration":357,"startTime":"2022-02-13T09:37:35.305570228Z[Etc/UTC]","screenshots":[{"screenshot":"09ba4ee5ccac0aa636a9670d38e25fee663391b93e1647d75028bbdb3ef3b144.png","timeStamp":1644745055393},{"screenshot":"a385aec9d35a6fc7f4eb9c6069bbb0e4b3317c3d623e54fd3195ad5d99d9ebe7.png","timeStamp":1644745055663}],"result":"SUCCESS","precondition":false,"level":1,"children":[{"number":3,"description":"Adds todo items called: {}","duration":65,"startTime":"2022-02-13T09:37:35.596818522Z[Etc/UTC]","screenshots":[{"screenshot":"a385aec9d35a6fc7f4eb9c6069bbb0e4b3317c3d623e54fd3195ad5d99d9ebe7.png","timeStamp":1644745055659},{"screenshot":"a385aec9d35a6fc7f4eb9c6069bbb0e4b3317c3d623e54fd3195ad5d99d9ebe7.png","timeStamp":1644745055662}],"result":"SUCCESS","precondition":false,"level":2}]}]},{"number":4,"description":"Should see the correct website title","duration":8,"startTime":"2022-02-13T09:37:35.665495449Z[Etc/UTC]","screenshots":[{"screenshot":"a385aec9d35a6fc7f4eb9c6069bbb0e4b3317c3d623e54fd3195ad5d99d9ebe7.png","timeStamp":1644745055673}],"result":"SUCCESS","precondition":false,"level":0},{"number":5,"description":"Should see the correct application heading","duration":26,"startTime":"2022-02-13T09:37:35.674422887Z[Etc/UTC]","screenshots":[{"screenshot":"a385aec9d35a6fc7f4eb9c6069bbb0e4b3317c3d623e54fd3195ad5d99d9ebe7.png","timeStamp":1644745055700}],"result":"SUCCESS","precondition":false,"level":0},{"number":6,"description":"Should see the about section","duration":73,"startTime":"2022-02-13T09:37:35.701163103Z[Etc/UTC]","screenshots":[{"screenshot":"a385aec9d35a6fc7f4eb9c6069bbb0e4b3317c3d623e54fd3195ad5d99d9ebe7.png","timeStamp":1644745055774}],"result":"SUCCESS","precondition":false,"level":0}],"userStory":{"id":"net.serenitybdd.demos.todos.pageobjects.features.accessing_the_application.LearnAboutTheApplication","storyName":"Learn about the application","displayName":"Learn about the application","storyClassName":"net.serenitybdd.demos.todos.pageobjects.features.accessing_the_application.LearnAboutTheApplication","path":"net.serenitybdd.demos.todos.pageobjects.features.accessing_the_application","type":"feature"},"featureTag":{"name":"Accessing the application/Learn about the application","type":"feature","displayName":"Accessing the application/Learn about the application"},"title":"Should be able to identify the application with page objects","tags":[{"name":"RELEASE-1","type":"version","displayName":"RELEASE-1"},{"name":"Accessing the application/Learn about the application","type":"feature","displayName":"Accessing the application/Learn about the application"},{"name":"Accessing the application","type":"capability","displayName":"Accessing the application"},{"name":"PageObjects pattern","type":"tag","displayName":"PageObjects pattern"}],"startTime":"2022-02-13T09:37:34.431614448Z[Etc/UTC]","duration":1343,"projectKey":"","sessionId":"6b3e8c441bc8841047bf29fae34e3ed0","driver":"chrome","isManualTestingUpToDate":false,"manual":false,"testSource":"JUnit","order":0,"result":"SUCCESS","versions":["RELEASE-1"]}