{"name":"View only the completed items","id":"filtering-todos;view-only-the-completed-items","scenarioId":"classpath:features/cucumber/maintain_my_todo_list/filtering_todos:View only the completed items","methodName":"View only the completed items","testSteps":[{"number":1,"description":"Given that Jane has a todo list containing Buy some milk, Walk the dog","duration":5456,"startTime":"2023-08-20T07:03:25.300853371Z[Etc/UTC]","result":"SUCCESS","precondition":false,"level":0,"children":[{"number":2,"description":"Jane starts with a todo list containing Buy some milk, Walk the dog","duration":5140,"startTime":"2023-08-20T07:03:25.559289820Z[Etc/UTC]","result":"SUCCESS","precondition":false,"level":1,"children":[{"number":3,"description":"Jane opens the home.page page","duration":3220,"startTime":"2023-08-20T07:03:25.757144349Z[Etc/UTC]","result":"SUCCESS","precondition":false,"level":2},{"number":4,"description":"Jane adds the todo items called: [Buy some milk, Walk the dog]","duration":1648,"startTime":"2023-08-20T07:03:29.050558781Z[Etc/UTC]","result":"SUCCESS","precondition":false,"level":2,"children":[{"number":5,"description":"Jane adds a todo item called: Buy some milk","duration":748,"startTime":"2023-08-20T07:03:29.237571646Z[Etc/UTC]","result":"SUCCESS","precondition":false,"level":3,"children":[{"number":6,"description":"Jane enters \u0027Buy some milk\u0027 then hits [RETURN] into \u0027What needs to be done?\u0027 field","duration":719,"startTime":"2023-08-20T07:03:29.265295145Z[Etc/UTC]","result":"SUCCESS","precondition":false,"level":4}]},{"number":7,"description":"Jane adds a todo item called: Walk the dog","duration":621,"startTime":"2023-08-20T07:03:30.077621564Z[Etc/UTC]","result":"SUCCESS","precondition":false,"level":3,"children":[{"number":8,"description":"Jane enters \u0027Walk the dog\u0027 then hits [RETURN] into \u0027What needs to be done?\u0027 field","duration":556,"startTime":"2023-08-20T07:03:30.141135907Z[Etc/UTC]","result":"SUCCESS","precondition":false,"level":4}]}]}]}]},{"number":9,"description":"And she completes the task called \"Walk the dog\"","duration":529,"startTime":"2023-08-20T07:03:30.757597501Z[Etc/UTC]","result":"SUCCESS","precondition":false,"level":0,"children":[{"number":10,"description":"she completes the item calledWalk the dog","duration":371,"startTime":"2023-08-20T07:03:30.824806410Z[Etc/UTC]","result":"SUCCESS","precondition":false,"level":1,"children":[{"number":11,"description":"she clicks on the complete item tick box","duration":347,"startTime":"2023-08-20T07:03:30.848618039Z[Etc/UTC]","result":"SUCCESS","precondition":false,"level":2}]}]},{"number":12,"description":"When she filters her list to show only Completed tasks","duration":581,"startTime":"2023-08-20T07:03:31.287636339Z[Etc/UTC]","result":"SUCCESS","precondition":false,"level":0,"children":[{"number":13,"description":"she filters items by Completed","duration":445,"startTime":"2023-08-20T07:03:31.423305781Z[Etc/UTC]","result":"SUCCESS","precondition":false,"level":1,"children":[{"number":14,"description":"she clicks on filter by Completed","duration":392,"startTime":"2023-08-20T07:03:31.475424819Z[Etc/UTC]","result":"SUCCESS","precondition":false,"level":2}]}]},{"number":15,"description":"Then her todo list should contain Walk the dog","duration":196,"startTime":"2023-08-20T07:03:31.871160340Z[Etc/UTC]","result":"SUCCESS","precondition":false,"level":0,"children":[{"number":16,"description":"Then the items displayed should be ([Walk the dog])","duration":181,"startTime":"2023-08-20T07:03:31.885569500Z[Etc/UTC]","result":"SUCCESS","precondition":false,"level":1}]}],"userStory":{"id":"classpath:features/cucumber/maintain_my_todo_list/filtering_todos","storyName":"Filtering todos","displayName":"Filtering todos","path":"cucumber/maintain_my_todo_list/filtering_todos","pathElements":[{"name":"cucumber","description":""},{"name":"maintain_my_todo_list","description":""},{"name":"filtering_todos","description":""}],"narrative":"  In order to make me feel **a sense of accomplishment**\n  As a forgetful person\n  I want to be to _view all of things I have completed_","type":"feature"},"title":"View only the completed items","description":"","tags":[{"name":"cucumber","type":"tag","displayName":"cucumber"},{"name":"Linux","type":"context","displayName":"Linux"},{"name":"Chrome","type":"context","displayName":"Chrome"},{"name":"filtering","type":"tag","displayName":"filtering"},{"name":"Chrome, Linux","type":"context","displayName":"Chrome, Linux"}],"startTime":"2023-08-20T07:03:25.034257386Z[Etc/UTC]","duration":7033,"projectKey":"","driver":"chrome:jane","isManualTestingUpToDate":false,"context":"chrome,linux","manual":false,"testSource":"Cucumber","actors":[{"name":"Jane"}],"result":"SUCCESS"}