{"name":"The todo count should keep track of how many todos remain","id":"completing-todos;the-todo-count-should-keep-track-of-how-many-todos-remain","scenarioId":"classpath:features/cucumber/maintain_my_todo_list/completing_todos:The todo count should keep track of how many todos remain","methodName":"The todo count should keep track of how many todos remain","testSteps":[{"number":1,"description":"Given Jane has a todo list containing Buy some milk, Walk the dog","duration":4059,"startTime":"2024-01-13T14:13:20.521200972Z[Etc/UTC]","result":"SUCCESS","precondition":false,"level":0,"children":[{"number":2,"description":"Jane starts with a todo list containing Buy some milk, Walk the dog","duration":3760,"startTime":"2024-01-13T14:13:20.798645378Z[Etc/UTC]","result":"SUCCESS","precondition":false,"level":1,"children":[{"number":3,"description":"Jane opens the home.page page","duration":2560,"startTime":"2024-01-13T14:13:20.818344377Z[Etc/UTC]","result":"SUCCESS","precondition":false,"level":2},{"number":4,"description":"Jane adds the todo items called: [Buy some milk, Walk the dog]","duration":1161,"startTime":"2024-01-13T14:13:23.394940213Z[Etc/UTC]","result":"SUCCESS","precondition":false,"level":2,"children":[{"number":5,"description":"Jane adds a todo item called: Buy some milk","duration":587,"startTime":"2024-01-13T14:13:23.435286271Z[Etc/UTC]","result":"SUCCESS","precondition":false,"level":3,"children":[{"number":6,"description":"Jane enters \u0027Buy some milk\u0027 then hits [RETURN] into \u0027What needs to be done?\u0027 field","duration":571,"startTime":"2024-01-13T14:13:23.436690069Z[Etc/UTC]","result":"SUCCESS","precondition":false,"level":4}]},{"number":7,"description":"Jane adds a todo item called: Walk the dog","duration":494,"startTime":"2024-01-13T14:13:24.057815688Z[Etc/UTC]","result":"SUCCESS","precondition":false,"level":3,"children":[{"number":8,"description":"Jane enters \u0027Walk the dog\u0027 then hits [RETURN] into \u0027What needs to be done?\u0027 field","duration":488,"startTime":"2024-01-13T14:13:24.059102519Z[Etc/UTC]","result":"SUCCESS","precondition":false,"level":4}]}]}]}]},{"number":9,"description":"Then her remaining todo count should be 2","duration":648,"startTime":"2024-01-13T14:13:24.582657747Z[Etc/UTC]","result":"SUCCESS","precondition":false,"level":0,"children":[{"number":10,"description":"her should see the number of items left that is equal to: \u003c2\u003e","duration":351,"startTime":"2024-01-13T14:13:24.695487093Z[Etc/UTC]","result":"SUCCESS","precondition":false,"level":1}]},{"number":11,"description":"When she completes the task called \"Walk the dog\"","duration":336,"startTime":"2024-01-13T14:13:25.389594106Z[Etc/UTC]","result":"SUCCESS","precondition":false,"level":0,"children":[{"number":12,"description":"she completes the item called Walk the dog","duration":312,"startTime":"2024-01-13T14:13:25.392999882Z[Etc/UTC]","result":"SUCCESS","precondition":false,"level":1,"children":[{"number":13,"description":"she clicks on the complete item tick box","duration":308,"startTime":"2024-01-13T14:13:25.394116567Z[Etc/UTC]","result":"SUCCESS","precondition":false,"level":2}]}]},{"number":14,"description":"Then her remaining todo count should be 1","duration":270,"startTime":"2024-01-13T14:13:25.728216403Z[Etc/UTC]","result":"SUCCESS","precondition":false,"level":0,"children":[{"number":15,"description":"her should see the number of items left that is equal to: \u003c1\u003e","duration":218,"startTime":"2024-01-13T14:13:25.730298079Z[Etc/UTC]","result":"SUCCESS","precondition":false,"level":1}]}],"userStory":{"id":"classpath:features/cucumber/maintain_my_todo_list/completing_todos","storyName":"Completing todos","displayName":"Completing todos","path":"cucumber/maintain_my_todo_list/completing_todos","pathElements":[{"name":"cucumber","description":""},{"name":"maintain_my_todo_list","description":""},{"name":"completing_todos","description":""}],"narrative":"  In order to make me feel **a sense of accomplishment**\n  As a forgetful person\n  I want to be to _view all of things I have completed_","type":"feature"},"title":"The todo count should keep track of how many todos remain","description":"","tags":[{"name":"cucumber","type":"tag","displayName":"cucumber"},{"name":"completing","type":"tag","displayName":"completing"},{"name":"Linux","type":"context","displayName":"Linux"},{"name":"Chrome","type":"context","displayName":"Chrome"},{"name":"Chrome, Linux","type":"context","displayName":"Chrome, Linux"}],"startTime":"2024-01-13T14:13:20.473745511Z[Etc/UTC]","duration":5810,"projectKey":"","driver":"chrome:jane","isManualTestingUpToDate":false,"context":"chrome,linux","manual":false,"testSource":"Cucumber","actors":[{"name":"Jane"}],"result":"SUCCESS"}