{"name":"should_be_able_to_view_only_completed_todos","id":"net.serenitybdd.demos.todos.screenplay.maintain_my_todo_list.FilteringTodos:should_be_able_to_view_only_completed_todos","scenarioId":"net.serenitybdd.demos.todos.screenplay.maintain_my_todo_list.FilteringTodos:should_be_able_to_view_only_completed_todos","testCaseName":"net.serenitybdd.demos.todos.screenplay.maintain_my_todo_list.FilteringTodos","methodName":"should_be_able_to_view_only_completed_todos","testSteps":[{"number":1,"description":"James starts with a todo list containing Walk the dog, Put out the garbage","duration":896,"startTime":"2023-08-20T07:04:42.012473944Z[Etc/UTC]","result":"SUCCESS","precondition":false,"level":0,"children":[{"number":2,"description":"James opens the home.page page","duration":510,"startTime":"2023-08-20T07:04:42.021257463Z[Etc/UTC]","result":"SUCCESS","precondition":false,"level":1},{"number":3,"description":"James adds the todo items called: [Walk the dog, Put out the garbage]","duration":367,"startTime":"2023-08-20T07:04:42.540502871Z[Etc/UTC]","result":"SUCCESS","precondition":false,"level":1,"children":[{"number":4,"description":"James adds a todo item called: Walk the dog","duration":191,"startTime":"2023-08-20T07:04:42.556371785Z[Etc/UTC]","result":"SUCCESS","precondition":false,"level":2,"children":[{"number":5,"description":"James enters \u0027Walk the dog\u0027 then hits [RETURN] into \u0027What needs to be done?\u0027 field","duration":172,"startTime":"2023-08-20T07:04:42.573741319Z[Etc/UTC]","result":"SUCCESS","precondition":false,"level":3}]},{"number":6,"description":"James adds a todo item called: Put out the garbage","duration":137,"startTime":"2023-08-20T07:04:42.769413560Z[Etc/UTC]","result":"SUCCESS","precondition":false,"level":2,"children":[{"number":7,"description":"James enters \u0027Put out the garbage\u0027 then hits [RETURN] into \u0027What needs to be done?\u0027 field","duration":130,"startTime":"2023-08-20T07:04:42.774952635Z[Etc/UTC]","result":"SUCCESS","precondition":false,"level":3}]}]}]},{"number":8,"description":"James completes the item calledWalk the dog","duration":90,"startTime":"2023-08-20T07:04:42.931187343Z[Etc/UTC]","result":"SUCCESS","precondition":false,"level":0,"children":[{"number":9,"description":"James clicks on the complete item tick box","duration":84,"startTime":"2023-08-20T07:04:42.935978608Z[Etc/UTC]","result":"SUCCESS","precondition":false,"level":1}]},{"number":10,"description":"James filters items by Completed","duration":89,"startTime":"2023-08-20T07:04:43.025399015Z[Etc/UTC]","result":"SUCCESS","precondition":false,"level":0,"children":[{"number":11,"description":"James clicks on filter by Completed","duration":83,"startTime":"2023-08-20T07:04:43.030143779Z[Etc/UTC]","result":"SUCCESS","precondition":false,"level":1}]},{"number":12,"description":"Then the items displayed should be iterable containing [\u0027Walk the dog\u0027]","duration":41,"startTime":"2023-08-20T07:04:43.119959491Z[Etc/UTC]","result":"SUCCESS","precondition":false,"level":0},{"number":13,"description":"Then the items displayed should be not iterable containing [\u0027Put out the garbage\u0027]","duration":21,"startTime":"2023-08-20T07:04:43.163023872Z[Etc/UTC]","result":"SUCCESS","precondition":false,"level":0},{"number":14,"description":"Then the current filter should be (Completed)","duration":23,"startTime":"2023-08-20T07:04:43.185543076Z[Etc/UTC]","result":"SUCCESS","precondition":false,"level":0}],"userStory":{"id":"net.serenitybdd.demos.todos.screenplay.maintain_my_todo_list.FilteringTodos","storyName":"FilteringTodos","displayName":"FilteringTodos","storyClassName":"net.serenitybdd.demos.todos.screenplay.maintain_my_todo_list.FilteringTodos","path":"screenplay.maintain_my_todo_list.FilteringTodos","pathElements":[{"name":"screenplay","description":"screenplay"},{"name":"maintain_my_todo_list","description":"maintain_my_todo_list"},{"name":"FilteringTodos","description":"FilteringTodos"}],"narrative":"","type":"feature"},"title":"Should be able to view only completed todos","tags":[{"name":"Linux","type":"context","displayName":"Linux"},{"name":"Chrome","type":"context","displayName":"Chrome"},{"name":"Chrome, Linux","type":"context","displayName":"Chrome, Linux"}],"startTime":"2023-08-20T07:04:41.991467861Z[Etc/UTC]","duration":538,"projectKey":"","sessionId":"0730229254d26419780a97d9cb97bf5a","driver":"chrome","isManualTestingUpToDate":false,"context":"chrome,linux","manual":false,"testSource":"JUnit","actors":[{"name":"James","can":["browse the web"]}],"order":0,"result":"SUCCESS"}