{"name":"should_not_affect_todos_belonging_to_another_user","id":"net.serenitybdd.demos.todos.screenplay.features.maintain_my_todo_list.TodosBelongToAUser:should_not_affect_todos_belonging_to_another_user","testCaseName":"net.serenitybdd.demos.todos.screenplay.features.maintain_my_todo_list.TodosBelongToAUser","testSteps":[{"number":1,"description":"James starts with a todo list containing Walk the dog, Put out the garbage","duration":885,"startTime":"2022-02-13T09:38:22.480645946Z[Etc/UTC]","screenshots":[{"screenshot":"b42dc3cf33e1f57509d809017d4714e96e8fed5cb1e79acebcc9ef0000a1b797.png","timeStamp":1644745103366}],"result":"SUCCESS","precondition":false,"level":0,"children":[{"number":2,"description":"James opens the home.page page","duration":542,"startTime":"2022-02-13T09:38:22.481899352Z[Etc/UTC]","screenshots":[{"screenshot":"a385aec9d35a6fc7f4eb9c6069bbb0e4b3317c3d623e54fd3195ad5d99d9ebe7.png","timeStamp":1644745103024}],"result":"SUCCESS","precondition":false,"level":1},{"number":3,"description":"James adds the todo items called: [Walk the dog, Put out the garbage]","duration":339,"startTime":"2022-02-13T09:38:23.025445420Z[Etc/UTC]","screenshots":[{"screenshot":"a385aec9d35a6fc7f4eb9c6069bbb0e4b3317c3d623e54fd3195ad5d99d9ebe7.png","timeStamp":1644745103027},{"screenshot":"b42dc3cf33e1f57509d809017d4714e96e8fed5cb1e79acebcc9ef0000a1b797.png","timeStamp":1644745103365}],"result":"SUCCESS","precondition":false,"level":1,"children":[{"number":4,"description":"James adds a todo item called: Walk the dog","duration":178,"startTime":"2022-02-13T09:38:23.030413245Z[Etc/UTC]","screenshots":[{"screenshot":"a385aec9d35a6fc7f4eb9c6069bbb0e4b3317c3d623e54fd3195ad5d99d9ebe7.png","timeStamp":1644745103033},{"screenshot":"0e6577c60c68378c42e68aa472b9404b98d695fcc72162bfcb206edf73452b01.png","timeStamp":1644745103208}],"result":"SUCCESS","precondition":false,"level":2,"children":[{"number":5,"description":"James enters \u0027Walk the dog\u0027 then hits [RETURN] into \u0027What needs to be done?\u0027 field","duration":172,"startTime":"2022-02-13T09:38:23.033712462Z[Etc/UTC]","screenshots":[{"screenshot":"a385aec9d35a6fc7f4eb9c6069bbb0e4b3317c3d623e54fd3195ad5d99d9ebe7.png","timeStamp":1644745103037},{"screenshot":"0e6577c60c68378c42e68aa472b9404b98d695fcc72162bfcb206edf73452b01.png","timeStamp":1644745103205}],"result":"SUCCESS","precondition":false,"level":3}]},{"number":6,"description":"James adds a todo item called: Put out the garbage","duration":150,"startTime":"2022-02-13T09:38:23.211957270Z[Etc/UTC]","screenshots":[{"screenshot":"0e6577c60c68378c42e68aa472b9404b98d695fcc72162bfcb206edf73452b01.png","timeStamp":1644745103214},{"screenshot":"b42dc3cf33e1f57509d809017d4714e96e8fed5cb1e79acebcc9ef0000a1b797.png","timeStamp":1644745103362}],"result":"SUCCESS","precondition":false,"level":2,"children":[{"number":7,"description":"James enters \u0027Put out the garbage\u0027 then hits [RETURN] into \u0027What needs to be done?\u0027 field","duration":144,"startTime":"2022-02-13T09:38:23.215016986Z[Etc/UTC]","screenshots":[{"screenshot":"0e6577c60c68378c42e68aa472b9404b98d695fcc72162bfcb206edf73452b01.png","timeStamp":1644745103218},{"screenshot":"b42dc3cf33e1f57509d809017d4714e96e8fed5cb1e79acebcc9ef0000a1b797.png","timeStamp":1644745103359}],"result":"SUCCESS","precondition":false,"level":3}]}]}]},{"number":8,"description":"Jane starts with a todo list containing Walk the dog, Feed the cat","duration":866,"startTime":"2022-02-13T09:38:23.367875564Z[Etc/UTC]","screenshots":[{"screenshot":"73f3eca50f98a89dd62f0726d65e96e3cd802c1e366323b896fe90b7d8a859b5.png","timeStamp":1644745104234}],"result":"SUCCESS","precondition":false,"level":0,"children":[{"number":9,"description":"Jane opens the home.page page","duration":535,"startTime":"2022-02-13T09:38:23.370053575Z[Etc/UTC]","screenshots":[{"screenshot":"a385aec9d35a6fc7f4eb9c6069bbb0e4b3317c3d623e54fd3195ad5d99d9ebe7.png","timeStamp":1644745103905}],"result":"SUCCESS","precondition":false,"level":1},{"number":10,"description":"Jane adds the todo items called: [Walk the dog, Feed the cat]","duration":326,"startTime":"2022-02-13T09:38:23.906500307Z[Etc/UTC]","screenshots":[{"screenshot":"a385aec9d35a6fc7f4eb9c6069bbb0e4b3317c3d623e54fd3195ad5d99d9ebe7.png","timeStamp":1644745103908},{"screenshot":"73f3eca50f98a89dd62f0726d65e96e3cd802c1e366323b896fe90b7d8a859b5.png","timeStamp":1644745104232}],"result":"SUCCESS","precondition":false,"level":1,"children":[{"number":11,"description":"Jane adds a todo item called: Walk the dog","duration":167,"startTime":"2022-02-13T09:38:23.911288931Z[Etc/UTC]","screenshots":[{"screenshot":"a385aec9d35a6fc7f4eb9c6069bbb0e4b3317c3d623e54fd3195ad5d99d9ebe7.png","timeStamp":1644745103914},{"screenshot":"0e6577c60c68378c42e68aa472b9404b98d695fcc72162bfcb206edf73452b01.png","timeStamp":1644745104078}],"result":"SUCCESS","precondition":false,"level":2,"children":[{"number":12,"description":"Jane enters \u0027Walk the dog\u0027 then hits [RETURN] into \u0027What needs to be done?\u0027 field","duration":159,"startTime":"2022-02-13T09:38:23.914653148Z[Etc/UTC]","screenshots":[{"screenshot":"a385aec9d35a6fc7f4eb9c6069bbb0e4b3317c3d623e54fd3195ad5d99d9ebe7.png","timeStamp":1644745103918},{"screenshot":"0e6577c60c68378c42e68aa472b9404b98d695fcc72162bfcb206edf73452b01.png","timeStamp":1644745104074}],"result":"SUCCESS","precondition":false,"level":3}]},{"number":13,"description":"Jane adds a todo item called: Feed the cat","duration":147,"startTime":"2022-02-13T09:38:24.082268302Z[Etc/UTC]","screenshots":[{"screenshot":"0e6577c60c68378c42e68aa472b9404b98d695fcc72162bfcb206edf73452b01.png","timeStamp":1644745104084},{"screenshot":"73f3eca50f98a89dd62f0726d65e96e3cd802c1e366323b896fe90b7d8a859b5.png","timeStamp":1644745104229}],"result":"SUCCESS","precondition":false,"level":2,"children":[{"number":14,"description":"Jane enters \u0027Feed the cat\u0027 then hits [RETURN] into \u0027What needs to be done?\u0027 field","duration":140,"startTime":"2022-02-13T09:38:24.085228217Z[Etc/UTC]","screenshots":[{"screenshot":"0e6577c60c68378c42e68aa472b9404b98d695fcc72162bfcb206edf73452b01.png","timeStamp":1644745104088},{"screenshot":"73f3eca50f98a89dd62f0726d65e96e3cd802c1e366323b896fe90b7d8a859b5.png","timeStamp":1644745104225}],"result":"SUCCESS","precondition":false,"level":3}]}]}]},{"number":15,"description":"James completes the item called: Walk the dog","duration":157,"startTime":"2022-02-13T09:38:24.237576893Z[Etc/UTC]","screenshots":[{"screenshot":"0de01da8c3f98d9218c849d74dfd2121e318f48d48ee26d7dea5417e4cb7bae3.png","timeStamp":1644745104394}],"result":"SUCCESS","precondition":false,"level":0,"children":[{"number":16,"description":"James clicks on the complete item tick box","duration":153,"startTime":"2022-02-13T09:38:24.239155401Z[Etc/UTC]","screenshots":[{"screenshot":"0de01da8c3f98d9218c849d74dfd2121e318f48d48ee26d7dea5417e4cb7bae3.png","timeStamp":1644745104392}],"result":"SUCCESS","precondition":false,"level":1}]},{"number":17,"description":"James clears all the completed items","duration":131,"startTime":"2022-02-13T09:38:24.395405497Z[Etc/UTC]","screenshots":[{"screenshot":"e9a6833d83cd1db0844436d001a41d6633dac88399b5d0aafd77b175a5b73084.png","timeStamp":1644745104526}],"result":"SUCCESS","precondition":false,"level":0,"children":[{"number":18,"description":"James clicks on Clear completed link","duration":127,"startTime":"2022-02-13T09:38:24.397490207Z[Etc/UTC]","screenshots":[{"screenshot":"e9a6833d83cd1db0844436d001a41d6633dac88399b5d0aafd77b175a5b73084.png","timeStamp":1644745104524}],"result":"SUCCESS","precondition":false,"level":1}]},{"number":19,"description":"Then the items displayed should be iterable containing [\u0027Walk the dog\u0027, \u0027Feed the cat\u0027]","duration":32,"startTime":"2022-02-13T09:38:24.527571570Z[Etc/UTC]","screenshots":[{"screenshot":"e9a6833d83cd1db0844436d001a41d6633dac88399b5d0aafd77b175a5b73084.png","timeStamp":1644745104560}],"result":"SUCCESS","precondition":false,"level":0}],"userStory":{"id":"net.serenitybdd.demos.todos.screenplay.features.maintain_my_todo_list.TodosBelongToAUser","storyName":"Todos belong to a user","displayName":"Todos belong to a user","storyClassName":"net.serenitybdd.demos.todos.screenplay.features.maintain_my_todo_list.TodosBelongToAUser","path":"maintain_my_todo_list","type":"feature"},"featureTag":{"name":"Maintain my todo list/Todos belong to a user","type":"feature","displayName":"Maintain my todo list/Todos belong to a user"},"title":"Should not affect todos belonging to another user","tags":[{"name":"Screenplay pattern","type":"tag","displayName":"Screenplay pattern"},{"name":"Maintain my todo list/Todos belong to a user","type":"feature","displayName":"Maintain my todo list/Todos belong to a user"},{"name":"RELEASE-3","type":"version","displayName":"RELEASE-3"},{"name":"Maintain my todo list","type":"capability","displayName":"Maintain my todo list"}],"startTime":"2022-02-13T09:38:22.476094523Z[Etc/UTC]","duration":2084,"projectKey":"","sessionId":"d855c4bec992d2441f78e2b377165050","driver":"chrome","isManualTestingUpToDate":false,"manual":false,"testSource":"JUnit","actors":[{"name":"James","can":["browse the web"]},{"name":"Jane","can":["browse the web"]}],"order":0,"result":"SUCCESS","versions":["RELEASE-3"]}